axios/__init__.py
axios/async_client.py
axios/core.py
axios/fastapi.py
axios/http_client.py
axios/rate_limiter.py
axios/types.py
axios_py-0.1.1.dist-info/METADATA
axios_py-0.1.1.dist-info/WHEEL
axios_py-0.1.1.dist-info/licenses/LICENSE
axios_py-0.1.1.dist-info/RECORD
