Metadata-Version: 2.4
Name: axios-py
Version: 0.1.1
Summary: Python HTTP client inspired by Axios
Project-URL: Homepage, https://github.com/avijitsen/axios-py
Author-email: Avijit Sen <avijitsen@example.com>
License: MIT
License-File: LICENSE
Classifier: Development Status :: 3 - Alpha
Classifier: Intended Audience :: Developers
Classifier: License :: OSI Approved :: MIT License
Classifier: Programming Language :: Python :: 3
Classifier: Programming Language :: Python :: 3.7
Classifier: Programming Language :: Python :: 3.8
Classifier: Programming Language :: Python :: 3.9
Classifier: Programming Language :: Python :: 3.10
Classifier: Programming Language :: Python :: 3.11
Requires-Python: >=3.8
Requires-Dist: aiohttp>=3.8.0
Requires-Dist: urllib3>=2.0.0
Provides-Extra: dev
Requires-Dist: black>=22.0.0; extra == 'dev'
Requires-Dist: isort>=5.0.0; extra == 'dev'
Requires-Dist: mypy>=1.0.0; extra == 'dev'
Requires-Dist: pytest-asyncio>=0.18.0; extra == 'dev'
Requires-Dist: pytest-cov>=4.0.0; extra == 'dev'
Requires-Dist: pytest>=7.0.0; extra == 'dev'
Requires-Dist: ruff>=0.0.200; extra == 'dev'
Provides-Extra: fastapi
Requires-Dist: fastapi>=0.68.0; extra == 'fastapi'
Requires-Dist: uvicorn>=0.15.0; extra == 'fastapi'
